multiversx_sdk_cli/__init__.py
multiversx_sdk_cli/args_converter.py
multiversx_sdk_cli/args_validation.py
multiversx_sdk_cli/cli.py
multiversx_sdk_cli/cli_config.py
multiversx_sdk_cli/cli_config_env.py
multiversx_sdk_cli/cli_config_wallet.py
multiversx_sdk_cli/cli_contracts.py
multiversx_sdk_cli/cli_data.py
multiversx_sdk_cli/cli_delegation.py
multiversx_sdk_cli/cli_deps.py
multiversx_sdk_cli/cli_dns.py
multiversx_sdk_cli/cli_faucet.py
multiversx_sdk_cli/cli_get.py
multiversx_sdk_cli/cli_governance.py
multiversx_sdk_cli/cli_ledger.py
multiversx_sdk_cli/cli_localnet.py
multiversx_sdk_cli/cli_multisig.py
multiversx_sdk_cli/cli_output.py
multiversx_sdk_cli/cli_password.py
multiversx_sdk_cli/cli_shared.py
multiversx_sdk_cli/cli_tokens.py
multiversx_sdk_cli/cli_transactions.py
multiversx_sdk_cli/cli_validator_wallet.py
multiversx_sdk_cli/cli_validators.py
multiversx_sdk_cli/cli_wallet.py
multiversx_sdk_cli/config.py
multiversx_sdk_cli/config_env.py
multiversx_sdk_cli/config_wallet.py
multiversx_sdk_cli/constants.py
multiversx_sdk_cli/contract_verification.py
multiversx_sdk_cli/cosign_transaction.py
multiversx_sdk_cli/dns.py
multiversx_sdk_cli/docker.py
multiversx_sdk_cli/downloader.py
multiversx_sdk_cli/errors.py
multiversx_sdk_cli/guardian_relayer_data.py
multiversx_sdk_cli/guards.py
multiversx_sdk_cli/interfaces.py
multiversx_sdk_cli/myprocess.py
multiversx_sdk_cli/sign_verify.py
multiversx_sdk_cli/signing_wrapper.py
multiversx_sdk_cli/simulation.py
multiversx_sdk_cli/transactions.py
multiversx_sdk_cli/utils.py
multiversx_sdk_cli/ux.py
multiversx_sdk_cli/version.py
multiversx_sdk_cli/workstation.py
multiversx_sdk_cli/dependencies/__init__.py
multiversx_sdk_cli/dependencies/install.py
multiversx_sdk_cli/dependencies/modules.py
multiversx_sdk_cli/dependencies/resolution.py
multiversx_sdk_cli/localnet/__init__.py
multiversx_sdk_cli/localnet/config_default.py
multiversx_sdk_cli/localnet/config_general.py
multiversx_sdk_cli/localnet/config_networking.py
mxpy-11.2.3.dist-info/METADATA
mxpy-11.2.3.dist-info/WHEEL
mxpy-11.2.3.dist-info/entry_points.txt
mxpy-11.2.3.dist-info/licenses/LICENSE
mxpy-11.2.3.dist-info/RECORD
